{"index.md":"94e5d906","components_antd-btn_index.md":"ad572487","components_check-box_index.md":"689b9321","components_status_index.md":"fc90ceda","components_avatar_index.md":"95842a39","components_collapse-container_index.md":"83bf265a","components_tinymce_index.md":"6e257a94","components_button_index.md":"4a2e39bc","components_drag-drop_index.md":"b5d46e00","components_card_index.md":"3db2f7af","components_descriptions_index.md":"41b0a923","components_bpmn-viewer_index.md":"e692512f","components_count-down_index.md":"9f1e6d92","components_count-to_index.md":"bbb1b097","components_modal_index.md":"08b7810e","components_radio_index.md":"6468b33e","introduce.md":"02be5a3b","team.md":"4c57bc3c","components_rate_index.md":"5d5e2ca2","components_scroll-container_index.md":"3b2c3798","components_cropper_index.md":"c19d90db","components_divider_index.md":"f48aec44","components_virtual-scroll_index.md":"d028f09a","components_calendar_index.md":"6843fd07","components_icon_index.md":"2e8434d7","components_tree_index.md":"be0202c9","components_tabs_index.md":"6b7bd0a6","components_basic-drawer_index.md":"d19c0778","components_splitter_index.md":"d8feaf48","components_excel_index.md":"0d952ed4","components_shadow-dom_index.md":"c0703ee8","components_ripple_index.md":"ccc48ab1"}
